loqusdb/__init__.py
loqusdb/__main__.py
loqusdb/build_models/__init__.py
loqusdb/build_models/case.py
loqusdb/build_models/profile_variant.py
loqusdb/build_models/variant.py
loqusdb/commands/__init__.py
loqusdb/commands/annotate.py
loqusdb/commands/cli.py
loqusdb/commands/delete.py
loqusdb/commands/export.py
loqusdb/commands/identity.py
loqusdb/commands/load.py
loqusdb/commands/load_profile.py
loqusdb/commands/migrate.py
loqusdb/commands/restore.py
loqusdb/commands/update.py
loqusdb/commands/view.py
loqusdb/commands/wipe.py
loqusdb/constants/__init__.py
loqusdb/exceptions/__init__.py
loqusdb/exceptions/case.py
loqusdb/exceptions/profile.py
loqusdb/exceptions/vcf.py
loqusdb/log.py
loqusdb/models/__init__.py
loqusdb/models/case.py
loqusdb/models/identity.py
loqusdb/models/profile_variant.py
loqusdb/models/variant.py
loqusdb/plugins/__init__.py
loqusdb/plugins/mongo/__init__.py
loqusdb/plugins/mongo/adapter.py
loqusdb/plugins/mongo/case.py
loqusdb/plugins/mongo/profile_variant.py
loqusdb/plugins/mongo/structural_variant.py
loqusdb/plugins/mongo/variant.py
loqusdb/resources/__init__.py
loqusdb/resources/loqusdb.20181005.gz
loqusdb/resources/maf_50_sites_GRCh37.vcf.gz
loqusdb/resources/maf_50_sites_GRCh38.vcf.gz
loqusdb/utils/__init__.py
loqusdb/utils/annotate.py
loqusdb/utils/case.py
loqusdb/utils/delete.py
loqusdb/utils/load.py
loqusdb/utils/migrate.py
loqusdb/utils/profiling.py
loqusdb/utils/update.py
loqusdb/utils/variant.py
loqusdb/utils/vcf.py
loqusdb-2.7.25.dist-info/LICENSE
loqusdb-2.7.25.dist-info/METADATA
loqusdb-2.7.25.dist-info/WHEEL
loqusdb-2.7.25.dist-info/entry_points.txt
loqusdb-2.7.25.dist-info/RECORD
