Metadata-Version: 2.3
Name: loqusdb
Version: 2.7.25
Summary: A simple observation count database
License: MIT
Author: Mans Magnuson
Author-email: monsunas@gmail.com
Maintainer: Clinical Genomics Bioinformatics Team
Requires-Python: >=3.12,<4.0
Classifier: License :: OSI Approved :: MIT License
Classifier: Programming Language :: Python :: 3
Classifier: Programming Language :: Python :: 3.12
Classifier: Programming Language :: Python :: 3.13
Requires-Dist: PyYAML
Requires-Dist: click
Requires-Dist: coloredlogs
Requires-Dist: cyvcf2
Requires-Dist: mongo-adapter
Requires-Dist: numpy
Requires-Dist: ped_parser
Requires-Dist: pymongo
Requires-Dist: setuptools
Requires-Dist: vcftoolbox
